mcp_contract_builder/__init__.py
mcp_contract_builder/cli.py
mcp_contract_builder/runtime/builder.py
mcp_contract_builder/server.py
mcp_contract_builder-0.0.7.dist-info/METADATA
mcp_contract_builder-0.0.7.dist-info/WHEEL
mcp_contract_builder-0.0.7.dist-info/entry_points.txt
mcp_contract_builder-0.0.7.dist-info/RECORD
