Metadata-Version: 2.4
Name: mcp-contract-builder
Version: 0.0.7
Summary: Contract builder MCP tool (simple|auto|llm) without execution
Author: Codex Agent
Author-email: agent@example.com
Requires-Python: >=3.11,<4.0
Classifier: Programming Language :: Python :: 3
Classifier: Programming Language :: Python :: 3.11
Classifier: Programming Language :: Python :: 3.12
Classifier: Programming Language :: Python :: 3.13
Classifier: Programming Language :: Python :: 3.14
Requires-Dist: fastmcp (>=0.3.0,<0.4.0)
Requires-Dist: mcp (==1.25.0)
